eisenmp_examples/__init__.py
eisenmp_examples/cmd.py
eisenmp_examples/database.db
eisenmp_examples/eisenmp_exa_bruteforce.py
eisenmp_examples/eisenmp_exa_double_q.py
eisenmp_examples/eisenmp_exa_each_flask_orm_srv_one_cpu.py
eisenmp_examples/eisenmp_exa_entry.py
eisenmp_examples/eisenmp_exa_http.py
eisenmp_examples/eisenmp_exa_multi_srv_each_cpu.py
eisenmp_examples/eisenmp_exa_prime.py
eisenmp_examples/eisenmp_exa_web_csv.py
eisenmp_examples/__pycache__/__init__.cpython-310.pyc
eisenmp_examples/__pycache__/eisenmp_exa_bruteforce.cpython-310.pyc
eisenmp_examples/__pycache__/eisenmp_exa_double_q.cpython-310.pyc
eisenmp_examples/__pycache__/eisenmp_exa_each_flask_orm_srv_one_cpu.cpython-310.pyc
eisenmp_examples/__pycache__/eisenmp_exa_entry.cpython-310.pyc
eisenmp_examples/__pycache__/eisenmp_exa_http.cpython-310.pyc
eisenmp_examples/__pycache__/eisenmp_exa_multi_srv_each_cpu.cpython-310.pyc
eisenmp_examples/__pycache__/eisenmp_exa_prime.cpython-310.pyc
eisenmp_examples/__pycache__/eisenmp_exa_web_csv.cpython-310.pyc
eisenmp_examples/test/__init__.py
eisenmp_examples/test/test_entry.py
eisenmp_examples/utils_exa/__init__.py
eisenmp_examples/utils_exa/db_exa.db
eisenmp_examples/utils_exa/db_exa_schema.sql
eisenmp_examples/utils_exa/eisenmp_download.py
eisenmp_examples/utils_exa/eisenmp_search.py
eisenmp_examples/utils_exa/eisenmp_utils.py
eisenmp_examples/utils_exa/__pycache__/__init__.cpython-310.pyc
eisenmp_examples/utils_exa/__pycache__/eisenmp_download.cpython-310.pyc
eisenmp_examples/utils_exa/__pycache__/eisenmp_search.cpython-310.pyc
eisenmp_examples/utils_exa/__pycache__/eisenmp_utils.cpython-310.pyc
eisenmp_examples/worker/__init__.py
eisenmp_examples/worker/eisenmp_exa_wrk_bf_bruteforce.py
eisenmp_examples/worker/eisenmp_exa_wrk_bf_reduce.py
eisenmp_examples/worker/eisenmp_exa_wrk_csv.py
eisenmp_examples/worker/eisenmp_exa_wrk_double.py
eisenmp_examples/worker/eisenmp_exa_wrk_flask_orm_srv_one_cpu.py
eisenmp_examples-0.5.1.dist-info/LICENSE
eisenmp_examples-0.5.1.dist-info/LICENSE.rst
eisenmp_examples-0.5.1.dist-info/METADATA
eisenmp_examples-0.5.1.dist-info/WHEEL
eisenmp_examples-0.5.1.dist-info/entry_points.txt
eisenmp_examples-0.5.1.dist-info/top_level.txt
eisenmp_examples-0.5.1.dist-info/zip-safe
eisenmp_examples-0.5.1.dist-info/RECORD
